bettercam/__init__.py
bettercam/bettercam.py
bettercam/_libs/__init__.py
bettercam/_libs/d3d11.py
bettercam/_libs/dxgi.py
bettercam/_libs/user32.py
bettercam/core/__init__.py
bettercam/core/device.py
bettercam/core/duplicator.py
bettercam/core/output.py
bettercam/core/stagesurf.py
bettercam/processor/__init__.py
bettercam/processor/base.py
bettercam/processor/cupy_processor.py
bettercam/processor/numpy_processor.py
bettercam/util/__init__.py
bettercam/util/io.py
bettercam/util/timer.py
bettercam-1.0.0.dist-info/LICENSE
bettercam-1.0.0.dist-info/METADATA
bettercam-1.0.0.dist-info/WHEEL
bettercam-1.0.0.dist-info/top_level.txt
bettercam-1.0.0.dist-info/RECORD
